CHANGELOG.txt
LICENCE.txt
MANIFEST.in
README.txt
setup.py
joshbasiccalculator.egg-info/SOURCES.txt
joshbasiccalculator.egg-info/dependency_links.txt
joshbasiccalculator.egg-info/top_level.txt
joshbasiccalculatoran/__init__.py
joshbasiccalculatoran.egg-info/PKG-INFO
joshbasiccalculatoran.egg-info/SOURCES.txt
joshbasiccalculatoran.egg-info/dependency_links.txt
joshbasiccalculatoran.egg-info/top_level.txt